{"assets":{"A9C4C48B86369EC1E059B38BC6369DC3":{"type":"texture","index":1,"assetRequest":{"type":"slide","state":"contents","slide":"none"},"url":{"native":"assets/D37DB9C4-CA6C-4DC7-AAE0-3942D0CFD105.pdf"},"width":1024,"height":768},"C803FEAFFF4609326E020801129685AE":{"type":"texture","index":0,"assetRequest":{"type":"slide","state":"contents","slide":"none"},"url":{"native":"assets/D37DB9C4-CA6C-4DC7-AAE0-3942D0CFD105.pdf"},"width":1024,"height":768}},"events":[{"effects":[{"beginTime":0,"baseLayer":{"animations":[],"initialState":{"affineTransform":[1,0,0,1,0,0],"masksToBounds":false,"rotation":0,"scale":1,"position":{"pointX":512,"pointY":384},"width":1024,"sublayerTransform":[1,0,0,0,0,1,0,0,0,0,1,0,0,0,0,1],"contentsRect":{"y":0,"x":0,"width":1,"height":1},"opacity":1,"edgeAntialiasingMask":251658240,"height":768,"hidden":false,"anchorPoint":{"pointX":0.5,"pointY":0.5}},"objectID":"0","layers":[{"animations":[],"initialState":{"affineTransform":[1,0,0,1,0,0],"masksToBounds":false,"rotation":0,"scale":1,"position":{"pointX":512,"pointY":384},"width":1024,"sublayerTransform":[1,0,0,0,0,1,0,0,0,0,1,-0.0004922987690640373,0,0,0,1],"contentsRect":{"y":0,"x":0,"width":1,"height":1},"opacity":1,"edgeAntialiasingMask":251658240,"height":768,"hidden":false,"anchorPoint":{"pointX":0.5,"pointY":0.5}},"layers":[{"animations":[],"layers":[],"texturedRectangle":{"isBackgroundTexture":false,"singleTextureOpacity":1,"textureType":0,"textBaseline":0,"textXHeight":0,"isVerticalText":false},"initialState":{"affineTransform":[1,0,0,1,0,0],"masksToBounds":false,"rotation":0,"scale":1,"position":{"pointX":512,"pointY":384},"width":1024,"sublayerTransform":[1,0,0,0,0,1,0,0,0,0,1,0,0,0,0,1],"contentsRect":{"y":0,"x":0,"width":1,"height":1},"opacity":1,"edgeAntialiasingMask":0,"height":768,"hidden":false,"anchorPoint":{"pointX":0.5,"pointY":0.5}},"texture":"A9C4C48B86369EC1E059B38BC6369DC3"},{"animations":[{"timeOffset":0,"from":{"scalar":false},"beginTime":0,"repeatCount":0,"fillMode":"both","property":"hidden","autoreverses":false,"duration":0.01,"to":{"scalar":true}}],"layers":[],"texturedRectangle":{"isBackgroundTexture":false,"singleTextureOpacity":1,"textureType":0,"textBaseline":0,"textXHeight":0,"isVerticalText":false},"initialState":{"affineTransform":[1,0,0,1,0,0],"masksToBounds":false,"rotation":0,"scale":1,"position":{"pointX":512,"pointY":384},"width":1024,"sublayerTransform":[1,0,0,0,0,1,0,0,0,0,1,0,0,0,0,1],"contentsRect":{"y":0,"x":0,"width":1,"height":1},"opacity":1,"edgeAntialiasingMask":0,"height":768,"hidden":false,"anchorPoint":{"pointX":0.5,"pointY":0.5}},"texture":"C803FEAFFF4609326E020801129685AE"}]}]},"effects":[],"duration":0.01,"type":"transition","name":"none","objectID":"0"}],"automaticPlay":false,"hyperlinks":[],"accessibility":[{"text":"Text","targetRectangle":{"y":40,"x":36,"width":55.01484382152557,"height":28}},{"text":"environment variables","targetRectangle":{"y":125,"x":36,"width":383.7599999999999,"height":48.400146484375}},{"text":"\tAWS_SECRET_ACCESS_KEY: Secret key for a user with the required permissions.","targetRectangle":{"y":220,"x":60.49999988219315,"width":902.0524001178064,"height":52.59999966621399}},{"text":"\tAWS_ACCESS_KEY_ID: Access key for a user with the required permissions.","targetRectangle":{"y":272.599999666214,"x":60.49999988219315,"width":847.0744001178067,"height":52.59999966621399}},{"text":"\tAWS_DEFAULT_REGION: Region where the target AWS CodeDeploy application is.","targetRectangle":{"y":325.199999332428,"x":60.49999988219315,"width":908.8830001178068,"height":85.59999966621399}},{"text":"\tAPPLICATION_NAME: Name of AWS CodeDeploy application.","targetRectangle":{"y":410.799998998642,"x":60.49999988219315,"width":705.0360001178069,"height":52.59999966621399}},{"text":"\tDEPLOYMENT_CONFIG: AWS CodeDeploy Deployment Configuration (CodeDeployDefault.OneAtATime|CodeDeployDefault.AllAtOnce|CodeDeployDefault.HalfAtATime|Custom).","targetRectangle":{"y":463.399998664856,"x":60.49999988219315,"width":803.5204001178067,"height":118.599999666214}},{"text":"\tDEPLOYMENT_GROUP_NAME: Name of the Deployment group in the application.","targetRectangle":{"y":581.9999983310699,"x":60.49999988219315,"width":925.6858001178069,"height":52.59999966621399}},{"text":"\tS3_BUCKET: Name of the S3 Bucket where source code to be deployed is stored.","targetRectangle":{"y":634.5999979972839,"x":60.49999988219315,"width":907.0028001178069,"height":33}}],"baseLayer":{"animations":[],"initialState":{"affineTransform":[1,0,0,1,0,0],"masksToBounds":false,"rotation":0,"scale":1,"position":{"pointX":512,"pointY":384},"width":1024,"sublayerTransform":[1,0,0,0,0,1,0,0,0,0,1,0,0,0,0,1],"contentsRect":{"y":0,"x":0,"width":1,"height":1},"opacity":1,"edgeAntialiasingMask":251658240,"height":768,"hidden":false,"anchorPoint":{"pointX":0.5,"pointY":0.5}},"objectID":"0","layers":[{"animations":[],"initialState":{"affineTransform":[1,0,0,1,0,0],"masksToBounds":false,"rotation":0,"scale":1,"position":{"pointX":512,"pointY":384},"width":1024,"sublayerTransform":[1,0,0,0,0,1,0,0,0,0,1,-0.0004922987690640373,0,0,0,1],"contentsRect":{"y":0,"x":0,"width":1,"height":1},"opacity":1,"edgeAntialiasingMask":251658240,"height":768,"hidden":false,"anchorPoint":{"pointX":0.5,"pointY":0.5}},"layers":[{"animations":[],"layers":[],"texturedRectangle":{"isBackgroundTexture":false,"singleTextureOpacity":1,"textureType":0,"textBaseline":0,"textXHeight":0,"isVerticalText":false},"initialState":{"affineTransform":[1,0,0,1,0,0],"masksToBounds":false,"rotation":0,"scale":1,"position":{"pointX":512,"pointY":384},"width":1024,"sublayerTransform":[1,0,0,0,0,1,0,0,0,0,1,0,0,0,0,1],"contentsRect":{"y":0,"x":0,"width":1,"height":1},"opacity":1,"edgeAntialiasingMask":0,"height":768,"hidden":false,"anchorPoint":{"pointX":0.5,"pointY":0.5}},"texture":"C803FEAFFF4609326E020801129685AE"}]}]}}]}